{"areas/rhombus-dng.json/name":{"orig":"Rhombus Dungeon","text":"Підземелля Ромбу"},"areas/rhombus-dng.json/floors/0/name":{"orig":"1st Floor","text":"1-й поверх"},"areas/rhombus-dng.json/floors/0/maps/0/name":{"orig":"Entrance","text":"Вхід"},"areas/rhombus-dng.json/floors/0/maps/1/name":{"orig":"Puzzle Room 1","text":"Кімната-головоломка 1"},"areas/rhombus-dng.json/floors/0/maps/2/name":{"orig":"Puzzle Room 2","text":"Кімната-головоломка 2"},"areas/rhombus-dng.json/floors/0/maps/3/name":{"orig":"Ability Room 1","text":"Кімната здібності 1"},"areas/rhombus-dng.json/floors/1/name":{"orig":"2nd Floor","text":"2-й поверх"},"areas/rhombus-dng.json/floors/1/maps/0/name":{"orig":"Middle Room","text":"Центральна кімната"},"areas/rhombus-dng.json/floors/1/maps/1/name":{"orig":"Upper Path 1","text":"Верхній шлях 1"},"areas/rhombus-dng.json/floors/1/maps/2/name":{"orig":"Upper Path 2","text":"Верхній шлях 2"},"areas/rhombus-dng.json/floors/1/maps/3/name":{"orig":"Upper Path 3","text":"Верхній шлях 3"},"areas/rhombus-dng.json/floors/1/maps/4/name":{"orig":"Lower Path 1","text":"Нижній шлях 1"},"areas/rhombus-dng.json/floors/1/maps/5/name":{"orig":"Lower Path 2","text":"Нижній шлях 2"},"areas/rhombus-dng.json/floors/1/maps/6/name":{"orig":"Lower Path 3","text":"Нижній шлях 3"},"areas/rhombus-dng.json/floors/2/name":{"orig":"3rd Floor","text":"3-й поверх"},"areas/rhombus-dng.json/floors/2/maps/0/name":{"orig":"Ability Room 2","text":"Кімната випробувань 2"},"areas/rhombus-dng.json/floors/2/maps/1/name":{"orig":"Puzzle Room 3","text":"Кіманат-головоломка 3"},"areas/rhombus-dng.json/floors/2/maps/2/name":{"orig":"Boss Room","text":"Кімната босса"},"areas/rhombus-dng.json/floors/3/name":{"orig":"4th Floor","text":"4-й поверх"},"areas/rhombus-dng.json/floors/3/maps/0/name":{"orig":"Final Room","text":"Фінальна кімната"}}
